terrier.py
terrier-0.2.1.dist-info/DESCRIPTION.rst
terrier-0.2.1.dist-info/METADATA
terrier-0.2.1.dist-info/RECORD
terrier-0.2.1.dist-info/WHEEL
terrier-0.2.1.dist-info/entry_points.txt
terrier-0.2.1.dist-info/metadata.json
terrier-0.2.1.dist-info/top_level.txt
