Metadata-Version: 2.0
Name: terrier
Version: 0.2.1
Summary: UNKNOWN
Home-page: https://github.com/immunda/terrier
Author: Phil Howell
Author-email: phil@quae.co.uk
License: MIT
Platform: UNKNOWN
Requires-Dist: click
